worldathletics/__init__.py
worldathletics/air_quality_device_element_reads.py
worldathletics/air_quality_devices.py
worldathletics/async_base_client.py
worldathletics/base_model.py
worldathletics/client.py
worldathletics/competition_document.py
worldathletics/competitions_by_country.py
worldathletics/countries_by_event_id.py
worldathletics/current_record_holder.py
worldathletics/disciplines_by_event_id.py
worldathletics/enums.py
worldathletics/event_media.py
worldathletics/exceptions.py
worldathletics/get_all_competitions.py
worldathletics/get_all_event_phases_by_discipline.py
worldathletics/get_all_gold_tour_events.py
worldathletics/get_all_schedules.py
worldathletics/get_all_time_list.py
worldathletics/get_appearance.py
worldathletics/get_article.py
worldathletics/get_article_locations.py
worldathletics/get_articles.py
worldathletics/get_asset.py
worldathletics/get_assets.py
worldathletics/get_assets_dates.py
worldathletics/get_assets_total.py
worldathletics/get_athlete.py
worldathletics/get_athlete_profile_athlete_representative.py
worldathletics/get_athlete_representative_athlete_search.py
worldathletics/get_athlete_representative_directory.py
worldathletics/get_athlete_representative_profile.py
worldathletics/get_athlete_representative_top_list.py
worldathletics/get_athlete_results.py
worldathletics/get_banners.py
worldathletics/get_c_i_s_competitor_res_date.py
worldathletics/get_c_i_s_competitor_res_disp.py
worldathletics/get_c_i_s_single_competitor.py
worldathletics/get_calendar_competition_results.py
worldathletics/get_calendar_events.py
worldathletics/get_campaign.py
worldathletics/get_campaigns.py
worldathletics/get_carousel.py
worldathletics/get_championship_highlights.py
worldathletics/get_championship_qualifications.py
worldathletics/get_cis_competitor_res_date.py
worldathletics/get_cis_competitor_res_disp.py
worldathletics/get_cis_single_competitor.py
worldathletics/get_combined_points.py
worldathletics/get_competition_organiser_info.py
worldathletics-1.2.2.dist-info/LICENSE.md
worldathletics-1.2.2.dist-info/METADATA
worldathletics-1.2.2.dist-info/WHEEL
worldathletics-1.2.2.dist-info/top_level.txt
worldathletics-1.2.2.dist-info/RECORD
